{
  "required": true,
  "minVersion": "0.8",
  "package": "net.errorcraft.codecium.mixin",
  "refmap": "${mod_id}.refmap.json",
  "compatibilityLevel": "JAVA_18",
  "mixins": [
    "minecraft.nbt.NbtOpsExtender",
    "minecraft.resources.RegistryFileCodecExtender",
    "minecraft.resources.HolderSetCodecExtender",
    "minecraft.resources.RegistryFixedCodecExtender",
    "minecraft.util.dynamic.ExtraCodecsExtender",
    "mojang.serialization.CodecExtender",
    "mojang.serialization.DataResultExtender",
    "mojang.serialization.JavaOpsExtender",
    "mojang.serialization.JsonOpsExtender",
    "mojang.serialization.codecs.BaseMapCodecExtender",
    "mojang.serialization.codecs.DispatchedMapCodecExtender",
    "mojang.serialization.codecs.EitherCodecExtender",
    "mojang.serialization.codecs.FieldDecoderExtender",
    "mojang.serialization.codecs.KeyDispatchCodecExtender",
    "mojang.serialization.codecs.ListCodecExtender",
    "mojang.serialization.codecs.OptionalFieldCodecExtender",
    "mojang.serialization.codecs.XorCodecExtender"
  ],
  "injectors": {
    "defaultRequire": 1
  }
}
